Workbook

Sheet Run
A1: Field | B1: Value
A2: Run ID | B2: EN-FULL-05
A3: Language | B3: en
A4: Variant | B4: full
A5: Requirement count | B5: =COUNTA(QUAL!A2:A12)+COUNTA(ARCH!A2:A12)+COUNTA(NET!A2:A12)+COUNTA(SEC!A2:A12)+COUNTA(DATA!A2:A12)+COUNTA(EVID!A2:A12)+COUNTA(OPS!A2:A12)+COUNTA(SUPPORT!A2:A12)+COUNTA(IMPL!A2:A12)+COUNTA(SUPPLY!A2:A12)+COUNTA(LEGAL!A2:A12)+COUNTA(COMM!A2:A12) -> 132
A6: Output folder | B6: Demo-Kit/Cowork/cowork-rfi-rfp/runs/en/full/05/results
A7: Contract version | B7: 2026.10.13-v1
A8: State | B8: NEW
A9: Customer to verify live | B9: Woodgrove Bank
A10: Warning | B10: FICTIONAL DEMO. Only use an untouched run; never edit this master. No Save quote, sends or orders.
A11: Editing contract | B11: Edit I:P on question sheets, designated pricing inputs and Run B8 only. Keep IDs, questions, formats and formulas.
A12: Completion | B12: Every question needs an evidenced answer or explained OPEN/BLOCKED/GAP/REVIEW. N/A requires a proven condition. DRAFT only.

Sheet QUAL
A1: ID | B1: Parent | C1: Priority | D1: Requirement | E1: Format | F1: Max characters | G1: Applies when | H1: Evidence required | I1: Answer | J1: Status | K1: Source ID | L1: Version | M1: Section | N1: Cloud link | O1: Open point | P1: Review | Q1: Characters | R1: Limit check
A2: QUAL-01 | C2: MUST | D2: Identify the bidding legal entity, delivery scope and countries covered; distinguish subcontractors from Contoso. | E2: Concise text; evidence in source columns | F2: 450 | G2: Always | H2: Approved KB-QUAL section and actual link; external test/certificate when requested | Q2: =LEN(I2) -> 0 | R2: =IF(I2="","",IF(Q2<=F2,"OK","OVER"))
A3: QUAL-02 | C3: MUST | D3: Provide audited financial statements for the last three years and explain any missing year. | E3: Concise text; evidence in source columns | F3: 450 | G3: Always | H3: Approved KB-QUAL section and actual link; external test/certificate when requested | Q3: =LEN(I3) -> 0 | R3: =IF(I3="","",IF(Q3<=F3,"OK","OVER"))
A4: QUAL-03 | C4: MUST | D4: Name two reference projects with at least twelve banking sites; provide permission to contact each reference. | E4: Concise text; evidence in source columns | F4: 450 | G4: Always | H4: Approved KB-QUAL section and actual link; external test/certificate when requested | Q4: =LEN(I4) -> 0 | R4: =IF(I4="","",IF(Q4<=F4,"OK","OVER"))
A5: QUAL-04 | C5: MUST | D5: Describe the engineering team and evidence of current network qualifications; do not list unverified individuals. | E5: Concise text; evidence in source columns | F5: 450 | G5: Always | H5: Approved KB-QUAL section and actual link; external test/certificate when requested | Q5: =LEN(I5) -> 0 | R5: =IF(I5="","",IF(Q5<=F5,"OK","OVER"))
A6: QUAL-05 | C6: MUST | D6: Disclose sanctions-screening and anti-bribery controls, owners and the frequency of review. | E6: Concise text; evidence in source columns | F6: 450 | G6: Always | H6: Approved KB-QUAL section and actual link; external test/certificate when requested | Q6: =LEN(I6) -> 0 | R6: =IF(I6="","",IF(Q6<=F6,"OK","OVER"))
A7: QUAL-06 | C7: MUST | D7: State which subcontractors can access bank systems and how changes require bank approval. | E7: Concise text; evidence in source columns | F7: 450 | G7: Always | H7: Approved KB-QUAL section and actual link; external test/certificate when requested | Q7: =LEN(I7) -> 0 | R7: =IF(I7="","",IF(Q7<=F7,"OK","OVER"))
A8: QUAL-07 | C8: MUST | D8: Provide professional indemnity and cyber-insurance limits, expiry dates and actual policy evidence. | E8: Concise text; evidence in source columns | F8: 450 | G8: Always | H8: Approved KB-QUAL section and actual link; external test/certificate when requested | Q8: =LEN(I8) -> 0 | R8: =IF(I8="","",IF(Q8<=F8,"OK","OVER"))
A9: QUAL-08 | C9: MUST | D9: Explain how conflicts of interest are checked before assigning staff to this bank. | E9: Concise text; evidence in source columns | F9: 450 | G9: Always | H9: Approved KB-QUAL section and actual link; external test/certificate when requested | Q9: =LEN(I9) -> 0 | R9: =IF(I9="","",IF(Q9<=F9,"OK","OVER"))
A10: QUAL-09 | C10: SHOULD | D10: Provide an accessibility policy and evidence that operational documentation meets WCAG 2.2 AA. | E10: Concise text; evidence in source columns | F10: 450 | G10: Always | H10: Approved KB-QUAL section and actual link; external test/certificate when requested | Q10: =LEN(I10) -> 0 | R10: =IF(I10="","",IF(Q10<=F10,"OK","OVER"))
A11: QUAL-10 | C11: SHOULD | D11: Describe environmental and disposal controls with evidence, without claiming an unheld certification. | E11: Concise text; evidence in source columns | F11: 450 | G11: Always | H11: Approved KB-QUAL section and actual link; external test/certificate when requested | Q11: =LEN(I11) -> 0 | R11: =IF(I11="","",IF(Q11<=F11,"OK","OVER"))
A12: QUAL-11 | C12: SHOULD | D12: Identify the authority needed to sign a binding response and confirm whether this draft has it. | E12: Concise text; evidence in source columns | F12: 450 | G12: Always | H12: Approved KB-QUAL section and actual link; external test/certificate when requested | Q12: =LEN(I12) -> 0 | R12: =IF(I12="","",IF(Q12<=F12,"OK","OVER"))

Sheet ARCH
A1: ID | B1: Parent | C1: Priority | D1: Requirement | E1: Format | F1: Max characters | G1: Applies when | H1: Evidence required | I1: Answer | J1: Status | K1: Source ID | L1: Version | M1: Section | N1: Cloud link | O1: Open point | P1: Review | Q1: Characters | R1: Limit check
A2: ARCH-01 | C2: MUST | D2: Propose a segmented network for twelve sites with separate staff, guest, payment and management zones; show trust boundaries. | E2: Concise text; evidence in source columns | F2: 450 | G2: Always | H2: Approved KB-ARCH section and actual link; external test/certificate when requested | Q2: =LEN(I2) -> 0 | R2: =IF(I2="","",IF(Q2<=F2,"OK","OVER"))
A3: ARCH-02 | C3: MUST | D3: Explain how the design integrates with existing identity, DNS, monitoring and incident tools without assuming connectors. | E3: Concise text; evidence in source columns | F3: 450 | G3: Always | H3: Approved KB-ARCH section and actual link; external test/certificate when requested | Q3: =LEN(I3) -> 0 | R3: =IF(I3="","",IF(Q3<=F3,"OK","OVER"))
A4: ARCH-03 | C4: MUST | D4: Provide a topology showing redundant uplinks, failure domains and the points that remain single points of failure. | E4: Concise text; evidence in source columns | F4: 450 | G4: Always | H4: Approved KB-ARCH section and actual link; external test/certificate when requested | Q4: =LEN(I4) -> 0 | R4: =IF(I4="","",IF(Q4<=F4,"OK","OVER"))
A5: ARCH-04 | C5: MUST | D5: Describe the migration path from the bank's current VLANs and the information needed before final design. | E5: Concise text; evidence in source columns | F5: 450 | G5: Always | H5: Approved KB-ARCH section and actual link; external test/certificate when requested | Q5: =LEN(I5) -> 0 | R5: =IF(I5="","",IF(Q5<=F5,"OK","OVER"))
A6: ARCH-05 | C6: MUST | D6: Explain IP address management and overlapping ranges during coexistence; identify required bank approvals. | E6: Concise text; evidence in source columns | F6: 450 | G6: Always | H6: Approved KB-ARCH section and actual link; external test/certificate when requested | Q6: =LEN(I6) -> 0 | R6: =IF(I6="","",IF(Q6<=F6,"OK","OVER"))
A7: ARCH-06 | C7: MUST | D7: State the boundary between hardware supply, managed operations and the bank's own responsibilities. | E7: Concise text; evidence in source columns | F7: 450 | G7: Always | H7: Approved KB-ARCH section and actual link; external test/certificate when requested | Q7: =LEN(I7) -> 0 | R7: =IF(I7="","",IF(Q7<=F7,"OK","OVER"))
A8: ARCH-07 | C8: MUST | D8: Describe integration authentication, secret storage and rotation; provide evidence for any claimed automation. | E8: Concise text; evidence in source columns | F8: 450 | G8: Always | H8: Approved KB-ARCH section and actual link; external test/certificate when requested | Q8: =LEN(I8) -> 0 | R8: =IF(I8="","",IF(Q8<=F8,"OK","OVER"))
A9: ARCH-08 | C9: MUST | D9: Explain how configuration export avoids vendor lock-in and what cannot be exported. | E9: Concise text; evidence in source columns | F9: 450 | G9: Always | H9: Approved KB-ARCH section and actual link; external test/certificate when requested | Q9: =LEN(I9) -> 0 | R9: =IF(I9="","",IF(Q9<=F9,"OK","OVER"))
A10: ARCH-09 | C10: SHOULD | D10: Provide capacity assumptions for 400 endpoints per site and identify the measurements required to validate them. | E10: Concise text; evidence in source columns | F10: 450 | G10: Always | H10: Approved KB-ARCH section and actual link; external test/certificate when requested | Q10: =LEN(I10) -> 0 | R10: =IF(I10="","",IF(Q10<=F10,"OK","OVER"))
A11: ARCH-10 | C11: SHOULD | D11: Describe a lab validation plan including identity outage and upstream network failure. | E11: Concise text; evidence in source columns | F11: 450 | G11: Always | H11: Approved KB-ARCH section and actual link; external test/certificate when requested | Q11: =LEN(I11) -> 0 | R11: =IF(I11="","",IF(Q11<=F11,"OK","OVER"))
A12: ARCH-11 | C12: SHOULD | D12: Identify architecture decisions still requiring the bank's security and network teams. | E12: Concise text; evidence in source columns | F12: 450 | G12: Always | H12: Approved KB-ARCH section and actual link; external test/certificate when requested | Q12: =LEN(I12) -> 0 | R12: =IF(I12="","",IF(Q12<=F12,"OK","OVER"))

Sheet NET
A1: ID | B1: Parent | C1: Priority | D1: Requirement | E1: Format | F1: Max characters | G1: Applies when | H1: Evidence required | I1: Answer | J1: Status | K1: Source ID | L1: Version | M1: Section | N1: Cloud link | O1: Open point | P1: Review | Q1: Characters | R1: Limit check
A2: NET-01 | C2: MUST | D2: Confirm 10G uplinks on every offered access switch; reconcile the requested CMS-48P-POE with documented uplink capability. | E2: Concise text; evidence in source columns | F2: 450 | G2: Always | H2: Approved KB-NET section and actual link; external test/certificate when requested | Q2: =LEN(I2) -> 0 | R2: =IF(I2="","",IF(Q2<=F2,"OK","OVER"))
A3: NET-02 | C3: MUST | D3: Demonstrate the PoE power budget for 32 access points per site at 30 W each and explain any required extra switches. | E3: Watts, headroom and design exception | F3: 450 | G3: Always | H3: Approved KB-NET section and actual link; external test/certificate when requested | Q3: =LEN(I3) -> 0 | R3: =IF(I3="","",IF(Q3<=F3,"OK","OVER"))
A4: NET-03 | C4: MUST | D4: Specify optical modules, cable types, distances and compatibility evidence for each uplink. | E4: Concise text; evidence in source columns | F4: 450 | G4: Always | H4: Approved KB-NET section and actual link; external test/certificate when requested | Q4: =LEN(I4) -> 0 | R4: =IF(I4="","",IF(Q4<=F4,"OK","OVER"))
A5: NET-04 | C5: MUST | D5: Explain 802.1X and fallback behavior for devices without supplicants, including payment-terminal risk. | E5: Concise text; evidence in source columns | F5: 450 | G5: Always | H5: Approved KB-NET section and actual link; external test/certificate when requested | Q5: =LEN(I5) -> 0 | R5: =IF(I5="","",IF(Q5<=F5,"OK","OVER"))
A6: NET-05 | C6: MUST | D6: Confirm whether Wi-Fi 7 and legacy clients can coexist; identify survey and regulatory prerequisites. | E6: Concise text; evidence in source columns | F6: 450 | G6: Always | H6: Approved KB-NET section and actual link; external test/certificate when requested | Q6: =LEN(I6) -> 0 | R6: =IF(I6="","",IF(Q6<=F6,"OK","OVER"))
A7: NET-06 | C7: MUST | D7: Provide roaming latency evidence for voice clients, not just a marketing capability statement. | E7: Concise text; evidence in source columns | F7: 450 | G7: Always | H7: Approved KB-NET section and actual link; external test/certificate when requested | Q7: =LEN(I7) -> 0 | R7: =IF(I7="","",IF(Q7<=F7,"OK","OVER"))
A8: NET-07 | C8: MUST | D8: Explain guest isolation and how guest traffic is prevented from reaching payment systems. | E8: Concise text; evidence in source columns | F8: 450 | G8: Always | H8: Approved KB-NET section and actual link; external test/certificate when requested | Q8: =LEN(I8) -> 0 | R8: =IF(I8="","",IF(Q8<=F8,"OK","OVER"))
A9: NET-08 | C9: MUST | D9: State throughput with security inspection enabled and supply independently measured results. | E9: Concise text; evidence in source columns | F9: 450 | G9: Always | H9: Approved KB-NET section and actual link; external test/certificate when requested | Q9: =LEN(I9) -> 0 | R9: =IF(I9="","",IF(Q9<=F9,"OK","OVER"))
A10: NET-09 | C10: SHOULD | D10: Describe multicast and QoS configuration for voice/video, including validation under congestion. | E10: Concise text; evidence in source columns | F10: 450 | G10: Always | H10: Approved KB-NET section and actual link; external test/certificate when requested | Q10: =LEN(I10) -> 0 | R10: =IF(I10="","",IF(Q10<=F10,"OK","OVER"))
A11: NET-10 | C11: SHOULD | D11: Confirm rack, power and cooling requirements and list site-survey gaps. | E11: Concise text; evidence in source columns | F11: 450 | G11: Always | H11: Approved KB-NET section and actual link; external test/certificate when requested | Q11: =LEN(I11) -> 0 | R11: =IF(I11="","",IF(Q11<=F11,"OK","OVER"))
A12: NET-11 | C12: SHOULD | D12: Describe tested configuration backup and restore including firmware-version compatibility. | E12: Concise text; evidence in source columns | F12: 450 | G12: Always | H12: Approved KB-NET section and actual link; external test/certificate when requested | Q12: =LEN(I12) -> 0 | R12: =IF(I12="","",IF(Q12<=F12,"OK","OVER"))

Sheet SEC
A1: ID | B1: Parent | C1: Priority | D1: Requirement | E1: Format | F1: Max characters | G1: Applies when | H1: Evidence required | I1: Answer | J1: Status | K1: Source ID | L1: Version | M1: Section | N1: Cloud link | O1: Open point | P1: Review | Q1: Characters | R1: Limit check
A2: SEC-01 | C2: MUST | D2: Does the management console support SAML 2.0 SSO and bank-controlled MFA? State the supported boundary. | E2: Yes/No/Partial + scope | F2: 160 | G2: Always | H2: Approved KB-SEC section and actual link; external test/certificate when requested | Q2: =LEN(I2) -> 0 | R2: =IF(I2="","",IF(Q2<=F2,"OK","OVER"))
A3: SEC-02 | B3: SEC-01 | C3: MUST | D3: If SSO is supported, prove SCIM deprovisioning within five minutes, including a measured test. | E3: Yes/No/Partial + measured minutes | F3: 450 | G3: If SSO is supported | H3: Approved KB-SEC section and actual link; external test/certificate when requested | Q3: =LEN(I3) -> 0 | R3: =IF(I3="","",IF(Q3<=F3,"OK","OVER"))
A4: SEC-03 | C4: MUST | D4: Describe least-privilege roles and segregation between bank operators and supplier administrators. | E4: Concise text; evidence in source columns | F4: 450 | G4: Always | H4: Approved KB-SEC section and actual link; external test/certificate when requested | Q4: =LEN(I4) -> 0 | R4: =IF(I4="","",IF(Q4<=F4,"OK","OVER"))
A5: SEC-04 | C5: MUST | D5: State encryption protocols and key ownership for management traffic and stored configuration. | E5: Concise text; evidence in source columns | F5: 450 | G5: Always | H5: Approved KB-SEC section and actual link; external test/certificate when requested | Q5: =LEN(I5) -> 0 | R5: =IF(I5="","",IF(Q5<=F5,"OK","OVER"))
A6: SEC-05 | C6: MUST | D6: Provide independent penetration-test evidence no older than twelve months and remediation status. | E6: Concise text; evidence in source columns | F6: 450 | G6: Always | H6: Approved KB-SEC section and actual link; external test/certificate when requested | Q6: =LEN(I6) -> 0 | R6: =IF(I6="","",IF(Q6<=F6,"OK","OVER"))
A7: SEC-06 | C7: MUST | D7: Explain critical vulnerability handling with a 48-hour mitigation requirement and escalation. | E7: Concise text; evidence in source columns | F7: 450 | G7: Always | H7: Approved KB-SEC section and actual link; external test/certificate when requested | Q7: =LEN(I7) -> 0 | R7: =IF(I7="","",IF(Q7<=F7,"OK","OVER"))
A8: SEC-07 | C8: MUST | D8: Show immutable audit retention for 365 days, export options and evidence of tamper resistance. | E8: Concise text; evidence in source columns | F8: 450 | G8: Always | H8: Approved KB-SEC section and actual link; external test/certificate when requested | Q8: =LEN(I8) -> 0 | R8: =IF(I8="","",IF(Q8<=F8,"OK","OVER"))
A9: SEC-08 | C9: MUST | D9: Describe emergency administrator access, dual control and the audit trail. | E9: Concise text; evidence in source columns | F9: 450 | G9: Always | H9: Approved KB-SEC section and actual link; external test/certificate when requested | Q9: =LEN(I9) -> 0 | R9: =IF(I9="","",IF(Q9<=F9,"OK","OVER"))
A10: SEC-09 | C10: SHOULD | D10: Explain secure firmware provenance, update verification and rollback constraints. | E10: Concise text; evidence in source columns | F10: 450 | G10: Always | H10: Approved KB-SEC section and actual link; external test/certificate when requested | Q10: =LEN(I10) -> 0 | R10: =IF(I10="","",IF(Q10<=F10,"OK","OVER"))
A11: SEC-10 | C11: SHOULD | D11: State whether a software bill of materials is supplied for each firmware release and provide one. | E11: Concise text; evidence in source columns | F11: 450 | G11: Always | H11: Approved KB-SEC section and actual link; external test/certificate when requested | Q11: =LEN(I11) -> 0 | R11: =IF(I11="","",IF(Q11<=F11,"OK","OVER"))
A12: SEC-11 | C12: SHOULD | D12: Identify residual security risks that require bank acceptance before production. | E12: Concise text; evidence in source columns | F12: 450 | G12: Always | H12: Approved KB-SEC section and actual link; external test/certificate when requested | Q12: =LEN(I12) -> 0 | R12: =IF(I12="","",IF(Q12<=F12,"OK","OVER"))

Sheet DATA
A1: ID | B1: Parent | C1: Priority | D1: Requirement | E1: Format | F1: Max characters | G1: Applies when | H1: Evidence required | I1: Answer | J1: Status | K1: Source ID | L1: Version | M1: Section | N1: Cloud link | O1: Open point | P1: Review | Q1: Characters | R1: Limit check
A2: DATA-01 | C2: MUST | D2: Can all management telemetry and backups remain exclusively in the EU with no non-EU administrator access? | E2: Yes/No/Partial + locations | F2: 450 | G2: Always | H2: Approved KB-DATA section and actual link; external test/certificate when requested | Q2: =LEN(I2) -> 0 | R2: =IF(I2="","",IF(Q2<=F2,"OK","OVER"))
A3: DATA-02 | B3: DATA-01 | C3: MUST | D3: If any non-EU processing is required, identify countries, subprocessors, transfer safeguards and missing approvals. | E3: Concise text; evidence in source columns | F3: 450 | G3: If processing is not exclusively EU | H3: Approved KB-DATA section and actual link; external test/certificate when requested | Q3: =LEN(I3) -> 0 | R3: =IF(I3="","",IF(Q3<=F3,"OK","OVER"))
A4: DATA-03 | C4: MUST | D4: List personal data categories, purposes and legal roles separately for telemetry and support. | E4: Concise text; evidence in source columns | F4: 450 | G4: Always | H4: Approved KB-DATA section and actual link; external test/certificate when requested | Q4: =LEN(I4) -> 0 | R4: =IF(I4="","",IF(Q4<=F4,"OK","OVER"))
A5: DATA-04 | C5: MUST | D5: Provide the signed data processing agreement for this bank, not an unsigned template. | E5: Concise text; evidence in source columns | F5: 450 | G5: Always | H5: Approved KB-DATA section and actual link; external test/certificate when requested | Q5: =LEN(I5) -> 0 | R5: =IF(I5="","",IF(Q5<=F5,"OK","OVER"))
A6: DATA-05 | C6: MUST | D6: State retention periods by data type and explain how deletion is evidenced. | E6: Concise text; evidence in source columns | F6: 450 | G6: Always | H6: Approved KB-DATA section and actual link; external test/certificate when requested | Q6: =LEN(I6) -> 0 | R6: =IF(I6="","",IF(Q6<=F6,"OK","OVER"))
A7: DATA-06 | C7: MUST | D7: Describe subject-access and deletion support, response times and bank responsibilities. | E7: Concise text; evidence in source columns | F7: 450 | G7: Always | H7: Approved KB-DATA section and actual link; external test/certificate when requested | Q7: =LEN(I7) -> 0 | R7: =IF(I7="","",IF(Q7<=F7,"OK","OVER"))
A8: DATA-07 | C8: MUST | D8: Confirm whether production data is used for analytics or AI training and cite an approved policy. | E8: Concise text; evidence in source columns | F8: 450 | G8: Always | H8: Approved KB-DATA section and actual link; external test/certificate when requested | Q8: =LEN(I8) -> 0 | R8: =IF(I8="","",IF(Q8<=F8,"OK","OVER"))
A9: DATA-08 | C9: MUST | D9: Explain minimization and masking in support bundles before external access. | E9: Concise text; evidence in source columns | F9: 450 | G9: Always | H9: Approved KB-DATA section and actual link; external test/certificate when requested | Q9: =LEN(I9) -> 0 | R9: =IF(I9="","",IF(Q9<=F9,"OK","OVER"))
A10: DATA-09 | C10: SHOULD | D10: Describe how privacy incidents are reported within the bank's required twelve-hour window. | E10: Concise text; evidence in source columns | F10: 450 | G10: Always | H10: Approved KB-DATA section and actual link; external test/certificate when requested | Q10: =LEN(I10) -> 0 | R10: =IF(I10="","",IF(Q10<=F10,"OK","OVER"))
A11: DATA-10 | C11: SHOULD | D11: Provide a data flow diagram with processing locations and a current subprocessor register. | E11: Concise text; evidence in source columns | F11: 450 | G11: Always | H11: Approved KB-DATA section and actual link; external test/certificate when requested | Q11: =LEN(I11) -> 0 | R11: =IF(I11="","",IF(Q11<=F11,"OK","OVER"))
A12: DATA-11 | C12: SHOULD | D12: Describe exit deletion including replicas, backups and the certification of completion. | E12: Concise text; evidence in source columns | F12: 450 | G12: Always | H12: Approved KB-DATA section and actual link; external test/certificate when requested | Q12: =LEN(I12) -> 0 | R12: =IF(I12="","",IF(Q12<=F12,"OK","OVER"))

Sheet EVID
A1: ID | B1: Parent | C1: Priority | D1: Requirement | E1: Format | F1: Max characters | G1: Applies when | H1: Evidence required | I1: Answer | J1: Status | K1: Source ID | L1: Version | M1: Section | N1: Cloud link | O1: Open point | P1: Review | Q1: Characters | R1: Limit check
A2: EVID-01 | C2: MUST | D2: Is the complete proposed service currently ISO 27001 certified? Provide evidence, not self-assessment. | E2: Yes/No/Unverified + evidence | F2: 160 | G2: Always | H2: Approved KB-EVID section and actual link; external test/certificate when requested | Q2: =LEN(I2) -> 0 | R2: =IF(I2="","",IF(Q2<=F2,"OK","OVER"))
A3: EVID-02 | B3: EVID-01 | C3: MUST | D3: If certified, supply certificate issuer, scope, number and expiry and map all exclusions to this service. | E3: Issuer, scope, number, expiry or unresolved dependency | F3: 450 | G3: If certification is confirmed; unknown parent remains unresolved | H3: Approved KB-EVID section and actual link; external test/certificate when requested | Q3: =LEN(I3) -> 0 | R3: =IF(I3="","",IF(Q3<=F3,"OK","OVER"))
A4: EVID-03 | C4: MUST | D4: Provide a current SOC 2 Type II report and identify its observation period and service coverage. | E4: Concise text; evidence in source columns | F4: 450 | G4: Always | H4: Approved KB-EVID section and actual link; external test/certificate when requested | Q4: =LEN(I4) -> 0 | R4: =IF(I4="","",IF(Q4<=F4,"OK","OVER"))
A5: EVID-04 | C5: MUST | D5: Map proposed payment-network controls to the bank's PCI requirements without claiming certification. | E5: Concise text; evidence in source columns | F5: 450 | G5: Always | H5: Approved KB-EVID section and actual link; external test/certificate when requested | Q5: =LEN(I5) -> 0 | R5: =IF(I5="","",IF(Q5<=F5,"OK","OVER"))
A6: EVID-05 | C6: MUST | D6: Provide independent evidence for claimed redundancy and failover times. | E6: Concise text; evidence in source columns | F6: 450 | G6: Always | H6: Approved KB-EVID section and actual link; external test/certificate when requested | Q6: =LEN(I6) -> 0 | R6: =IF(I6="","",IF(Q6<=F6,"OK","OVER"))
A7: EVID-06 | C7: MUST | D7: Supply the most recent disaster-recovery test record and list unresolved findings. | E7: Concise text; evidence in source columns | F7: 450 | G7: Always | H7: Approved KB-EVID section and actual link; external test/certificate when requested | Q7: =LEN(I7) -> 0 | R7: =IF(I7="","",IF(Q7<=F7,"OK","OVER"))
A8: EVID-07 | C8: MUST | D8: Show document ownership, approval date and version for every response-library source. | E8: Concise text; evidence in source columns | F8: 450 | G8: Always | H8: Approved KB-EVID section and actual link; external test/certificate when requested | Q8: =LEN(I8) -> 0 | R8: =IF(I8="","",IF(Q8<=F8,"OK","OVER"))
A9: EVID-08 | C9: MUST | D9: Explain how superseded documents are detected and excluded from current commitments. | E9: Concise text; evidence in source columns | F9: 450 | G9: Always | H9: Approved KB-EVID section and actual link; external test/certificate when requested | Q9: =LEN(I9) -> 0 | R9: =IF(I9="","",IF(Q9<=F9,"OK","OVER"))
A10: EVID-09 | C10: SHOULD | D10: List missing mandatory evidence and the accountable review function, without fabricated attachments. | E10: Concise text; evidence in source columns | F10: 450 | G10: Always | H10: Approved KB-EVID section and actual link; external test/certificate when requested | Q10: =LEN(I10) -> 0 | R10: =IF(I10="","",IF(Q10<=F10,"OK","OVER"))
A11: EVID-10 | C11: SHOULD | D11: Confirm the bank's right to inspect evidence under NDA and identify redacted items. | E11: Concise text; evidence in source columns | F11: 450 | G11: Always | H11: Approved KB-EVID section and actual link; external test/certificate when requested | Q11: =LEN(I11) -> 0 | R11: =IF(I11="","",IF(Q11<=F11,"OK","OVER"))
A12: EVID-11 | C12: SHOULD | D12: Provide a traceability register linking each requirement to an actual section and cloud file. | E12: Concise text; evidence in source columns | F12: 450 | G12: Always | H12: Approved KB-EVID section and actual link; external test/certificate when requested | Q12: =LEN(I12) -> 0 | R12: =IF(I12="","",IF(Q12<=F12,"OK","OVER"))

Sheet OPS
A1: ID | B1: Parent | C1: Priority | D1: Requirement | E1: Format | F1: Max characters | G1: Applies when | H1: Evidence required | I1: Answer | J1: Status | K1: Source ID | L1: Version | M1: Section | N1: Cloud link | O1: Open point | P1: Review | Q1: Characters | R1: Limit check
A2: OPS-01 | C2: MUST | D2: Commit to 99.95% 24/7 availability; reconcile any different SLA versions in the knowledge base. | E2: Concise text; evidence in source columns | F2: 450 | G2: Always | H2: Approved KB-OPS section and actual link; external test/certificate when requested | Q2: =LEN(I2) -> 0 | R2: =IF(I2="","",IF(Q2<=F2,"OK","OVER"))
A3: OPS-02 | C3: MUST | D3: Explain the availability denominator, maintenance exclusions and maximum service credits under the current SLA. | E3: Concise text; evidence in source columns | F3: 450 | G3: Always | H3: Approved KB-OPS section and actual link; external test/certificate when requested | Q3: =LEN(I3) -> 0 | R3: =IF(I3="","",IF(Q3<=F3,"OK","OVER"))
A4: OPS-03 | C4: MUST | D4: Describe monitoring coverage, alert ownership and the limits of the proposed managed service. | E4: Concise text; evidence in source columns | F4: 450 | G4: Always | H4: Approved KB-OPS section and actual link; external test/certificate when requested | Q4: =LEN(I4) -> 0 | R4: =IF(I4="","",IF(Q4<=F4,"OK","OVER"))
A5: OPS-04 | C5: MUST | D5: Define severity levels and response versus resolution targets; do not conflate the two. | E5: Concise text; evidence in source columns | F5: 450 | G5: Always | H5: Approved KB-OPS section and actual link; external test/certificate when requested | Q5: =LEN(I5) -> 0 | R5: =IF(I5="","",IF(Q5<=F5,"OK","OVER"))
A6: OPS-05 | C6: MUST | D6: Provide an escalation matrix for out-of-hours outages and state uncovered periods. | E6: Concise text; evidence in source columns | F6: 450 | G6: Always | H6: Approved KB-OPS section and actual link; external test/certificate when requested | Q6: =LEN(I6) -> 0 | R6: =IF(I6="","",IF(Q6<=F6,"OK","OVER"))
A7: OPS-06 | C7: MUST | D7: Describe change windows, bank sign-off and rollback ownership. | E7: Concise text; evidence in source columns | F7: 450 | G7: Always | H7: Approved KB-OPS section and actual link; external test/certificate when requested | Q7: =LEN(I7) -> 0 | R7: =IF(I7="","",IF(Q7<=F7,"OK","OVER"))
A8: OPS-07 | C8: MUST | D8: State patch cadence and emergency-change handling with evidence. | E8: Concise text; evidence in source columns | F8: 450 | G8: Always | H8: Approved KB-OPS section and actual link; external test/certificate when requested | Q8: =LEN(I8) -> 0 | R8: =IF(I8="","",IF(Q8<=F8,"OK","OVER"))
A9: OPS-08 | C9: MUST | D9: Specify operational dashboards, report frequency and which inputs the bank must provide. | E9: Concise text; evidence in source columns | F9: 450 | G9: Always | H9: Approved KB-OPS section and actual link; external test/certificate when requested | Q9: =LEN(I9) -> 0 | R9: =IF(I9="","",IF(Q9<=F9,"OK","OVER"))
A10: OPS-09 | C10: SHOULD | D10: Describe configuration drift detection and the approval needed to remediate it. | E10: Concise text; evidence in source columns | F10: 450 | G10: Always | H10: Approved KB-OPS section and actual link; external test/certificate when requested | Q10: =LEN(I10) -> 0 | R10: =IF(I10="","",IF(Q10<=F10,"OK","OVER"))
A11: OPS-10 | C11: SHOULD | D11: Explain how major incidents produce root-cause reports and corrective actions. | E11: Concise text; evidence in source columns | F11: 450 | G11: Always | H11: Approved KB-OPS section and actual link; external test/certificate when requested | Q11: =LEN(I11) -> 0 | R11: =IF(I11="","",IF(Q11<=F11,"OK","OVER"))
A12: OPS-11 | C12: SHOULD | D12: State service transition criteria before the supplier takes operational responsibility. | E12: Concise text; evidence in source columns | F12: 450 | G12: Always | H12: Approved KB-OPS section and actual link; external test/certificate when requested | Q12: =LEN(I12) -> 0 | R12: =IF(I12="","",IF(Q12<=F12,"OK","OVER"))

Sheet SUPPORT
A1: ID | B1: Parent | C1: Priority | D1: Requirement | E1: Format | F1: Max characters | G1: Applies when | H1: Evidence required | I1: Answer | J1: Status | K1: Source ID | L1: Version | M1: Section | N1: Cloud link | O1: Open point | P1: Review | Q1: Characters | R1: Limit check
A2: SUPPORT-01 | C2: MUST | D2: Can three-year next-business-day hardware care support the entire five-year term? Identify the renewal evidence gap. | E2: Concise text; evidence in source columns | F2: 450 | G2: Always | H2: Approved KB-SUPPORT section and actual link; external test/certificate when requested | Q2: =LEN(I2) -> 0 | R2: =IF(I2="","",IF(Q2<=F2,"OK","OVER"))
A3: SUPPORT-02 | C3: MUST | D3: Define business-day cutoffs, replacement logistics and geographic exclusions without promising four-hour replacement. | E3: Concise text; evidence in source columns | F3: 450 | G3: Always | H3: Approved KB-SUPPORT section and actual link; external test/certificate when requested | Q3: =LEN(I3) -> 0 | R3: =IF(I3="","",IF(Q3<=F3,"OK","OVER"))
A4: SUPPORT-03 | C4: MUST | D4: State support channels, languages and covered hours. | E4: Concise text; evidence in source columns | F4: 450 | G4: Always | H4: Approved KB-SUPPORT section and actual link; external test/certificate when requested | Q4: =LEN(I4) -> 0 | R4: =IF(I4="","",IF(Q4<=F4,"OK","OVER"))
A5: SUPPORT-04 | C5: MUST | D5: Describe responsibility for diagnosis versus hardware replacement. | E5: Concise text; evidence in source columns | F5: 450 | G5: Always | H5: Approved KB-SUPPORT section and actual link; external test/certificate when requested | Q5: =LEN(I5) -> 0 | R5: =IF(I5="","",IF(Q5<=F5,"OK","OVER"))
A6: SUPPORT-05 | C6: MUST | D6: Provide recovery-time and recovery-point objectives with supporting test evidence. | E6: Concise text; evidence in source columns | F6: 450 | G6: Always | H6: Approved KB-SUPPORT section and actual link; external test/certificate when requested | Q6: =LEN(I6) -> 0 | R6: =IF(I6="","",IF(Q6<=F6,"OK","OVER"))
A7: SUPPORT-06 | C7: MUST | D7: Explain resilience when the supplier's own service desk is unavailable. | E7: Concise text; evidence in source columns | F7: 450 | G7: Always | H7: Approved KB-SUPPORT section and actual link; external test/certificate when requested | Q7: =LEN(I7) -> 0 | R7: =IF(I7="","",IF(Q7<=F7,"OK","OVER"))
A8: SUPPORT-07 | C8: MUST | D8: Specify on-site spare holdings and who pays for unused or obsolete stock. | E8: Concise text; evidence in source columns | F8: 450 | G8: Always | H8: Approved KB-SUPPORT section and actual link; external test/certificate when requested | Q8: =LEN(I8) -> 0 | R8: =IF(I8="","",IF(Q8<=F8,"OK","OVER"))
A9: SUPPORT-08 | C9: MUST | D9: Describe end-user communications during an incident without assuming external-send permission. | E9: Concise text; evidence in source columns | F9: 450 | G9: Always | H9: Approved KB-SUPPORT section and actual link; external test/certificate when requested | Q9: =LEN(I9) -> 0 | R9: =IF(I9="","",IF(Q9<=F9,"OK","OVER"))
A10: SUPPORT-09 | C10: SHOULD | D10: Explain defect triage across hardware, firmware, identity and upstream networks. | E10: Concise text; evidence in source columns | F10: 450 | G10: Always | H10: Approved KB-SUPPORT section and actual link; external test/certificate when requested | Q10: =LEN(I10) -> 0 | R10: =IF(I10="","",IF(Q10<=F10,"OK","OVER"))
A11: SUPPORT-10 | C11: SHOULD | D11: Provide a verified continuity-test schedule and identify missing records. | E11: Concise text; evidence in source columns | F11: 450 | G11: Always | H11: Approved KB-SUPPORT section and actual link; external test/certificate when requested | Q11: =LEN(I11) -> 0 | R11: =IF(I11="","",IF(Q11<=F11,"OK","OVER"))
A12: SUPPORT-11 | C12: SHOULD | D12: Describe handover to a replacement supplier at contract end. | E12: Concise text; evidence in source columns | F12: 450 | G12: Always | H12: Approved KB-SUPPORT section and actual link; external test/certificate when requested | Q12: =LEN(I12) -> 0 | R12: =IF(I12="","",IF(Q12<=F12,"OK","OVER"))

Sheet IMPL
A1: ID | B1: Parent | C1: Priority | D1: Requirement | E1: Format | F1: Max characters | G1: Applies when | H1: Evidence required | I1: Answer | J1: Status | K1: Source ID | L1: Version | M1: Section | N1: Cloud link | O1: Open point | P1: Review | Q1: Characters | R1: Limit check
A2: IMPL-01 | C2: MUST | D2: Deliver twelve sites within six weeks; provide a gated plan and conditions rather than an unsupported date promise. | E2: Concise text; evidence in source columns | F2: 450 | G2: Always | H2: Approved KB-IMPL section and actual link; external test/certificate when requested | Q2: =LEN(I2) -> 0 | R2: =IF(I2="","",IF(Q2<=F2,"OK","OVER"))
A3: IMPL-02 | C3: MUST | D3: Define objective acceptance tests for segmentation, failover and throughput and who signs the results. | E3: Concise text; evidence in source columns | F3: 450 | G3: Always | H3: Approved KB-IMPL section and actual link; external test/certificate when requested | Q3: =LEN(I3) -> 0 | R3: =IF(I3="","",IF(Q3<=F3,"OK","OVER"))
A4: IMPL-03 | C4: MUST | D4: Specify the pilot site, go/no-go criteria and what happens after pilot failure. | E4: Concise text; evidence in source columns | F4: 450 | G4: Always | H4: Approved KB-IMPL section and actual link; external test/certificate when requested | Q4: =LEN(I4) -> 0 | R4: =IF(I4="","",IF(Q4<=F4,"OK","OVER"))
A5: IMPL-04 | C5: MUST | D5: List bank dependencies including access, cabling, power and identity configuration. | E5: Concise text; evidence in source columns | F5: 450 | G5: Always | H5: Approved KB-IMPL section and actual link; external test/certificate when requested | Q5: =LEN(I5) -> 0 | R5: =IF(I5="","",IF(Q5<=F5,"OK","OVER"))
A6: IMPL-05 | C6: MUST | D6: Provide training scope and evidence of operator readiness. | E6: Concise text; evidence in source columns | F6: 450 | G6: Always | H6: Approved KB-IMPL section and actual link; external test/certificate when requested | Q6: =LEN(I6) -> 0 | R6: =IF(I6="","",IF(Q6<=F6,"OK","OVER"))
A7: IMPL-06 | C7: MUST | D7: Describe the cutover window, outage notice and tested rollback plan. | E7: Concise text; evidence in source columns | F7: 450 | G7: Always | H7: Approved KB-IMPL section and actual link; external test/certificate when requested | Q7: =LEN(I7) -> 0 | R7: =IF(I7="","",IF(Q7<=F7,"OK","OVER"))
A8: IMPL-07 | C8: MUST | D8: Show project governance, decision rights and change control. | E8: Concise text; evidence in source columns | F8: 450 | G8: Always | H8: Approved KB-IMPL section and actual link; external test/certificate when requested | Q8: =LEN(I8) -> 0 | R8: =IF(I8="","",IF(Q8<=F8,"OK","OVER"))
A9: IMPL-08 | C9: MUST | D9: Define configuration documentation and asset-register handover deliverables. | E9: Concise text; evidence in source columns | F9: 450 | G9: Always | H9: Approved KB-IMPL section and actual link; external test/certificate when requested | Q9: =LEN(I9) -> 0 | R9: =IF(I9="","",IF(Q9<=F9,"OK","OVER"))
A10: IMPL-09 | C10: SHOULD | D10: Describe the method for validating RF coverage before and after installation. | E10: Concise text; evidence in source columns | F10: 450 | G10: Always | H10: Approved KB-IMPL section and actual link; external test/certificate when requested | Q10: =LEN(I10) -> 0 | R10: =IF(I10="","",IF(Q10<=F10,"OK","OVER"))
A11: IMPL-10 | C11: SHOULD | D11: Estimate on-site effort and separate included work from additional day rates. | E11: Concise text; evidence in source columns | F11: 450 | G11: Always | H11: Approved KB-IMPL section and actual link; external test/certificate when requested | Q11: =LEN(I11) -> 0 | R11: =IF(I11="","",IF(Q11<=F11,"OK","OVER"))
A12: IMPL-11 | C12: SHOULD | D12: State commercial consequences of bank-caused delays without automatically accepting penalties. | E12: Concise text; evidence in source columns | F12: 450 | G12: Always | H12: Approved KB-IMPL section and actual link; external test/certificate when requested | Q12: =LEN(I12) -> 0 | R12: =IF(I12="","",IF(Q12<=F12,"OK","OVER"))

Sheet SUPPLY
A1: ID | B1: Parent | C1: Priority | D1: Requirement | E1: Format | F1: Max characters | G1: Applies when | H1: Evidence required | I1: Answer | J1: Status | K1: Source ID | L1: Version | M1: Section | N1: Cloud link | O1: Open point | P1: Review | Q1: Characters | R1: Limit check
A2: SUPPLY-01 | C2: MUST | D2: The bill of materials requests 48 CAP-6E devices; verify lifecycle and propose CAP-7 only as a disclosed alternative. | E2: Concise text; evidence in source columns | F2: 450 | G2: Always | H2: Approved KB-SUPPLY section and actual link; external test/certificate when requested | Q2: =LEN(I2) -> 0 | R2: =IF(I2="","",IF(Q2<=F2,"OK","OVER"))
A3: SUPPLY-02 | B3: SUPPLY-01 | C3: MUST | D3: If available stock is insufficient, show dated allocation and delivery options without reserving or guaranteeing them. | E3: Concise text; evidence in source columns | F3: 450 | G3: If the requested or proposed line has insufficient stock | H3: Approved KB-SUPPLY section and actual link; external test/certificate when requested | Q3: =LEN(I3) -> 0 | R3: =IF(I3="","",IF(Q3<=F3,"OK","OVER"))
A4: SUPPLY-03 | C4: MUST | D4: For each line show on-hand, reserved and available quantities and distinguish a plan from a commitment. | E4: Concise text; evidence in source columns | F4: 450 | G4: Always | H4: Approved KB-SUPPLY section and actual link; external test/certificate when requested | Q4: =LEN(I4) -> 0 | R4: =IF(I4="","",IF(Q4<=F4,"OK","OVER"))
A5: SUPPLY-04 | C5: MUST | D5: Identify which alternatives need technical or bank approval and quantify price differences from live previews. | E5: Concise text; evidence in source columns | F5: 450 | G5: Always | H5: Approved KB-SUPPLY section and actual link; external test/certificate when requested | Q5: =LEN(I5) -> 0 | R5: =IF(I5="","",IF(Q5<=F5,"OK","OVER"))
A6: SUPPLY-05 | C6: MUST | D6: Explain split shipments and their impact on site sequencing and costs. | E6: Concise text; evidence in source columns | F6: 450 | G6: Always | H6: Approved KB-SUPPLY section and actual link; external test/certificate when requested | Q6: =LEN(I6) -> 0 | R6: =IF(I6="","",IF(Q6<=F6,"OK","OVER"))
A7: SUPPLY-06 | C7: MUST | D7: Provide lifecycle dates only where currently evidenced; do not turn an unknown date into a five-year warranty. | E7: Concise text; evidence in source columns | F7: 450 | G7: Always | H7: Approved KB-SUPPLY section and actual link; external test/certificate when requested | Q7: =LEN(I7) -> 0 | R7: =IF(I7="","",IF(Q7<=F7,"OK","OVER"))
A8: SUPPLY-07 | C8: MUST | D8: State incoterms, delivery locations and who bears transit risk. | E8: Concise text; evidence in source columns | F8: 450 | G8: Always | H8: Approved KB-SUPPLY section and actual link; external test/certificate when requested | Q8: =LEN(I8) -> 0 | R8: =IF(I8="","",IF(Q8<=F8,"OK","OVER"))
A9: SUPPLY-08 | C9: MUST | D9: Describe counterfeit prevention and serial-number traceability with actual evidence. | E9: Concise text; evidence in source columns | F9: 450 | G9: Always | H9: Approved KB-SUPPLY section and actual link; external test/certificate when requested | Q9: =LEN(I9) -> 0 | R9: =IF(I9="","",IF(Q9<=F9,"OK","OVER"))
A10: SUPPLY-09 | C10: SHOULD | D10: Show dependencies between optics, switches, gateways and care subscriptions before promising completeness. | E10: Concise text; evidence in source columns | F10: 450 | G10: Always | H10: Approved KB-SUPPLY section and actual link; external test/certificate when requested | Q10: =LEN(I10) -> 0 | R10: =IF(I10="","",IF(Q10<=F10,"OK","OVER"))
A11: SUPPLY-10 | C11: SHOULD | D11: Describe cancellation and substitution rules for delayed items. | E11: Concise text; evidence in source columns | F11: 450 | G11: Always | H11: Approved KB-SUPPLY section and actual link; external test/certificate when requested | Q11: =LEN(I11) -> 0 | R11: =IF(I11="","",IF(Q11<=F11,"OK","OVER"))
A12: SUPPLY-11 | C12: SHOULD | D12: Explain replenishment and replacement sourcing after product end of life. | E12: Concise text; evidence in source columns | F12: 450 | G12: Always | H12: Approved KB-SUPPLY section and actual link; external test/certificate when requested | Q12: =LEN(I12) -> 0 | R12: =IF(I12="","",IF(Q12<=F12,"OK","OVER"))

Sheet LEGAL
A1: ID | B1: Parent | C1: Priority | D1: Requirement | E1: Format | F1: Max characters | G1: Applies when | H1: Evidence required | I1: Answer | J1: Status | K1: Source ID | L1: Version | M1: Section | N1: Cloud link | O1: Open point | P1: Review | Q1: Characters | R1: Limit check
A2: LEGAL-01 | C2: MUST | D2: Accept unlimited liability, including indirect loss, or explicitly record a contractual exception. | E2: Accept/Exception + reason | F2: 160 | G2: Always | H2: Approved KB-LEGAL section and actual link; external test/certificate when requested | Q2: =LEN(I2) -> 0 | R2: =IF(I2="","",IF(Q2<=F2,"OK","OVER"))
A3: LEGAL-02 | B3: LEGAL-01 | C3: MUST | D3: If unlimited liability is not accepted, propose the approved counterposition and identify legal review requirements. | E3: Concise text; evidence in source columns | F3: 450 | G3: If unlimited liability is not accepted | H3: Approved KB-LEGAL section and actual link; external test/certificate when requested | Q3: =LEN(I3) -> 0 | R3: =IF(I3="","",IF(Q3<=F3,"OK","OVER"))
A4: LEGAL-03 | C4: MUST | D4: State the governing law, jurisdiction and which differences from bank terms remain unresolved. | E4: Concise text; evidence in source columns | F4: 450 | G4: Always | H4: Approved KB-LEGAL section and actual link; external test/certificate when requested | Q4: =LEN(I4) -> 0 | R4: =IF(I4="","",IF(Q4<=F4,"OK","OVER"))
A5: LEGAL-04 | C5: MUST | D5: Explain ownership of configurations, documentation and pre-existing intellectual property. | E5: Concise text; evidence in source columns | F5: 450 | G5: Always | H5: Approved KB-LEGAL section and actual link; external test/certificate when requested | Q5: =LEN(I5) -> 0 | R5: =IF(I5="","",IF(Q5<=F5,"OK","OVER"))
A6: LEGAL-05 | C6: MUST | D6: Describe termination assistance, duration and charges without assuming free unlimited transition. | E6: Concise text; evidence in source columns | F6: 450 | G6: Always | H6: Approved KB-LEGAL section and actual link; external test/certificate when requested | Q6: =LEN(I6) -> 0 | R6: =IF(I6="","",IF(Q6<=F6,"OK","OVER"))
A7: LEGAL-06 | C7: MUST | D7: Specify price-adjustment rights and whether any annual indexation has been agreed. | E7: Concise text; evidence in source columns | F7: 450 | G7: Always | H7: Approved KB-LEGAL section and actual link; external test/certificate when requested | Q7: =LEN(I7) -> 0 | R7: =IF(I7="","",IF(Q7<=F7,"OK","OVER"))
A8: LEGAL-07 | C8: MUST | D8: Provide audit rights and restrictions for third-party supplier facilities. | E8: Concise text; evidence in source columns | F8: 450 | G8: Always | H8: Approved KB-LEGAL section and actual link; external test/certificate when requested | Q8: =LEN(I8) -> 0 | R8: =IF(I8="","",IF(Q8<=F8,"OK","OVER"))
A9: LEGAL-08 | C9: MUST | D9: State warranty scope, remedies and exclusions using approved evidence rather than hidden API fields. | E9: Concise text; evidence in source columns | F9: 450 | G9: Always | H9: Approved KB-LEGAL section and actual link; external test/certificate when requested | Q9: =LEN(I9) -> 0 | R9: =IF(I9="","",IF(Q9<=F9,"OK","OVER"))
A10: LEGAL-09 | C10: SHOULD | D10: Describe delay penalties and limits that require commercial review. | E10: Concise text; evidence in source columns | F10: 450 | G10: Always | H10: Approved KB-LEGAL section and actual link; external test/certificate when requested | Q10: =LEN(I10) -> 0 | R10: =IF(I10="","",IF(Q10<=F10,"OK","OVER"))
A11: LEGAL-10 | C11: SHOULD | D11: Explain confidentiality and permitted use of bank information during bidding. | E11: Concise text; evidence in source columns | F11: 450 | G11: Always | H11: Approved KB-LEGAL section and actual link; external test/certificate when requested | Q11: =LEN(I11) -> 0 | R11: =IF(I11="","",IF(Q11<=F11,"OK","OVER"))
A12: LEGAL-11 | C12: SHOULD | D12: State explicitly that this draft does not constitute signature, contract acceptance or order creation. | E12: Concise text; evidence in source columns | F12: 450 | G12: Always | H12: Approved KB-LEGAL section and actual link; external test/certificate when requested | Q12: =LEN(I12) -> 0 | R12: =IF(I12="","",IF(Q12<=F12,"OK","OVER"))

Sheet COMM
A1: ID | B1: Parent | C1: Priority | D1: Requirement | E1: Format | F1: Max characters | G1: Applies when | H1: Evidence required | I1: Answer | J1: Status | K1: Source ID | L1: Version | M1: Section | N1: Cloud link | O1: Open point | P1: Review | Q1: Characters | R1: Limit check
A2: COMM-01 | C2: MUST | D2: Provide a five-year TCO in the customer's verified currency, separating hardware, implementation, operations and care renewals. | E2: Amount/currency or INCOMPLETE; pricing-sheet references | F2: 450 | G2: Always | H2: Approved KB-COMM section and actual link; external test/certificate when requested | Q2: =LEN(I2) -> 0 | R2: =IF(I2="","",IF(Q2<=F2,"OK","OVER"))
A3: COMM-02 | C3: MUST | D3: State years four and five renewal assumptions and mark TCO incomplete where no approved renewal price exists. | E3: Concise text; evidence in source columns | F3: 450 | G3: Always | H3: Approved KB-COMM section and actual link; external test/certificate when requested | Q3: =LEN(I3) -> 0 | R3: =IF(I3="","",IF(Q3<=F3,"OK","OVER"))
A4: COMM-03 | C4: MUST | D4: Show customer-specific unit net prices, quantities, discounts and source timestamps from the unsaved Atlas preview. | E4: Concise text; evidence in source columns | F4: 450 | G4: Always | H4: Approved KB-COMM section and actual link; external test/certificate when requested | Q4: =LEN(I4) -> 0 | R4: =IF(I4="","",IF(Q4<=F4,"OK","OVER"))
A5: COMM-04 | C5: MUST | D5: Reconcile line rounding, subtotal, tax and total against the preview, not an EUR list-price conversion. | E5: Reconciliation by line; amount/currency | F5: 450 | G5: Always | H5: Approved KB-COMM section and actual link; external test/certificate when requested | Q5: =LEN(I5) -> 0 | R5: =IF(I5="","",IF(Q5<=F5,"OK","OVER"))
A6: COMM-05 | C6: MUST | D6: Separate one-time, monthly and annual costs and state the unit and period of each rate. | E6: Concise text; evidence in source columns | F6: 450 | G6: Always | H6: Approved KB-COMM section and actual link; external test/certificate when requested | Q6: =LEN(I6) -> 0 | R6: =IF(I6="","",IF(Q6<=F6,"OK","OVER"))
A7: COMM-06 | C7: MUST | D7: Provide optional and mandatory costs separately without silently removing mandatory items from the total. | E7: Concise text; evidence in source columns | F7: 450 | G7: Always | H7: Approved KB-COMM section and actual link; external test/certificate when requested | Q7: =LEN(I7) -> 0 | R7: =IF(I7="","",IF(Q7<=F7,"OK","OVER"))
A8: COMM-07 | C8: MUST | D8: Explain payment terms, credit warnings and financing dependencies observed on the actual account. | E8: Concise text; evidence in source columns | F8: 450 | G8: Always | H8: Approved KB-COMM section and actual link; external test/certificate when requested | Q8: =LEN(I8) -> 0 | R8: =IF(I8="","",IF(Q8<=F8,"OK","OVER"))
A9: COMM-08 | C9: MUST | D9: State any price validity period as a draft assumption unless explicitly supported by current evidence. | E9: Concise text; evidence in source columns | F9: 450 | G9: Always | H9: Approved KB-COMM section and actual link; external test/certificate when requested | Q9: =LEN(I9) -> 0 | R9: =IF(I9="","",IF(Q9<=F9,"OK","OVER"))
A10: COMM-09 | C10: SHOULD | D10: Show how a switch or access-point substitution changes TCO without inventing a price. | E10: Concise text; evidence in source columns | F10: 450 | G10: Always | H10: Approved KB-COMM section and actual link; external test/certificate when requested | Q10: =LEN(I10) -> 0 | R10: =IF(I10="","",IF(Q10<=F10,"OK","OVER"))
A11: COMM-10 | C11: SHOULD | D11: Identify internal approval needs separately; do not expose supplier costs, margin or approval mechanics to the customer. | E11: Concise text; evidence in source columns | F11: 450 | G11: Always | H11: Approved KB-COMM section and actual link; external test/certificate when requested | Q11: =LEN(I11) -> 0 | R11: =IF(I11="","",IF(Q11<=F11,"OK","OVER"))
A12: COMM-11 | C12: SHOULD | D12: Provide an open-cost register so missing shipping, tax or renewal values cannot appear as confirmed zero. | E12: Concise text; evidence in source columns | F12: 450 | G12: Always | H12: Approved KB-COMM section and actual link; external test/certificate when requested | Q12: =LEN(I12) -> 0 | R12: =IF(I12="","",IF(Q12<=F12,"OK","OVER"))

Sheet Assumptions
A1: Assumption | B1: Value | C1: Source
A2: Years | B2: 5 | C2: Buyer RFI / COMM-01
A3: Months per year | B3: 12 | C3: KB-COMM v2 / section 2
A4: Required reporting currency | B4: USD | C4: Buyer RFI; verify live account currency. Do not invent FX.
A5: Sites | B5: 12 | C5: Buyer RFI / IMPL-01
A6: Monthly rate per site (USD) | B6: 240 | C6: KB-COMM v2 / section 2
A7: Currency rule | B7: No FX rate approved. Any mismatch stays open. | C7: KB-COMM v2 / section 3

Sheet Pricing
A1: SKU / cost | B1: Qty | C1: Unit net | D1: Currency | E1: Years / events | F1: Basis | G1: Net (currency in D) | H1: Source / timestamp | I1: Tax rate | J1: Tax | K1: Gross | L1: Review
A2: CMS-48P-POE | B2: 24 | E2: 1 | F2: One-time | G2: =IF(COUNT(B2,C2,E2)=3,ROUND(B2*ROUND(C2,2)*E2*IF(F2="Monthly",Assumptions!$B$3,1),2),"") | J2: =IF(COUNT(G2,I2)=2,ROUND(G2*I2,2),"") | K2: =IF(COUNT(G2,J2)=2,G2+J2,"")
A3: CAP-6E | B3: 48 | E3: 1 | F3: One-time | G3: =IF(COUNT(B3,C3,E3)=3,ROUND(B3*ROUND(C3,2)*E3*IF(F3="Monthly",Assumptions!$B$3,1),2),"") | J3: =IF(COUNT(G3,I3)=2,ROUND(G3*I3,2),"") | K3: =IF(COUNT(G3,J3)=2,G3+J3,"")
A4: CSFP-10G | B4: 48 | E4: 1 | F4: One-time | G4: =IF(COUNT(B4,C4,E4)=3,ROUND(B4*ROUND(C4,2)*E4*IF(F4="Monthly",Assumptions!$B$3,1),2),"") | J4: =IF(COUNT(G4,I4)=2,ROUND(G4*I4,2),"") | K4: =IF(COUNT(G4,J4)=2,G4+J4,"")
A5: CGW-500 | B5: 12 | E5: 1 | F5: One-time | G5: =IF(COUNT(B5,C5,E5)=3,ROUND(B5*ROUND(C5,2)*E5*IF(F5="Monthly",Assumptions!$B$3,1),2),"") | J5: =IF(COUNT(G5,I5)=2,ROUND(G5*I5,2),"") | K5: =IF(COUNT(G5,J5)=2,G5+J5,"")
A6: CARE-NET-3Y-NBD | B6: 24 | E6: 1 | F6: One-time | G6: =IF(COUNT(B6,C6,E6)=3,ROUND(B6*ROUND(C6,2)*E6*IF(F6="Monthly",Assumptions!$B$3,1),2),"") | J6: =IF(COUNT(G6,I6)=2,ROUND(G6*I6,2),"") | K6: =IF(COUNT(G6,J6)=2,G6+J6,"")
A7: SVC-NET-ASSESS | B7: 1 | E7: 1 | F7: One-time | G7: =IF(COUNT(B7,C7,E7)=3,ROUND(B7*ROUND(C7,2)*E7*IF(F7="Monthly",Assumptions!$B$3,1),2),"") | J7: =IF(COUNT(G7,I7)=2,ROUND(G7*I7,2),"") | K7: =IF(COUNT(G7,J7)=2,G7+J7,"")
A8: SVC-ONSITE-DAY | B8: 24 | E8: 1 | F8: One-time | G8: =IF(COUNT(B8,C8,E8)=3,ROUND(B8*ROUND(C8,2)*E8*IF(F8="Monthly",Assumptions!$B$3,1),2),"") | J8: =IF(COUNT(G8,I8)=2,ROUND(G8*I8,2),"") | K8: =IF(COUNT(G8,J8)=2,G8+J8,"")
A9: KB-managed-service | B9: =Assumptions!B5 -> 12 | C9: =Assumptions!B6 -> 240 | D9: USD | E9: =Assumptions!B2 -> 5 | F9: Monthly | G9: =IF(COUNT(B9,C9,E9)=3,ROUND(B9*ROUND(C9,2)*E9*IF(F9="Monthly",Assumptions!$B$3,1),2),"") -> 172800 | H9: KB-COMM v2 / section 2; tax unconfirmed | J9: =IF(COUNT(G9,I9)=2,ROUND(G9*I9,2),"") | K9: =IF(COUNT(G9,J9)=2,G9+J9,"")
A10: Care renewal years 4-5 | B10: 24 | E10: 2 | F10: Annual | G10: =IF(COUNT(B10,C10,E10)=3,ROUND(B10*ROUND(C10,2)*E10*IF(F10="Monthly",Assumptions!$B$3,1),2),"") | J10: =IF(COUNT(G10,I10)=2,ROUND(G10*I10,2),"") | K10: =IF(COUNT(G10,J10)=2,G10+J10,"")
A11: Freight | B11: 1 | E11: 1 | F11: One-time | G11: =IF(COUNT(B11,C11,E11)=3,ROUND(B11*ROUND(C11,2)*E11*IF(F11="Monthly",Assumptions!$B$3,1),2),"") | J11: =IF(COUNT(G11,I11)=2,ROUND(G11*I11,2),"") | K11: =IF(COUNT(G11,J11)=2,G11+J11,"")

Sheet TCO
A1: Measure | B1: Value | C1: Interpretation
A2: Reporting currency | B2: =Assumptions!B4 -> USD | C2: USD is a buyer requirement, not a claim about live Atlas.
A3: Known net subtotal | B3: =SUMIF(Pricing!D2:D11,Assumptions!B4,Pricing!G2:G11) -> 172800 | C3: PARTIAL: only populated amounts in reporting currency; never call this complete TCO.
A4: Complete required net TCO | B4: =IF(AND(COUNT(Pricing!G2:G11)=10,COUNTIF(Pricing!D2:D11,Assumptions!B4)=10),SUM(Pricing!G2:G11),"") | C4: Blank means missing price/period/currency; renewals and freight are mandatory.
A5: Complete gross TCO | B5: =IF(AND(COUNT(Pricing!K2:K11)=10,COUNTIF(Pricing!D2:D11,Assumptions!B4)=10),SUM(Pricing!K2:K11),"") | C5: Blank means incomplete taxes or other required amounts.
A6: Net coverage | B6: =IF(AND(COUNT(Pricing!G2:G11)=10,COUNTIF(Pricing!D2:D11,Assumptions!B4)=10),"COMPLETE","PARTIAL") -> PARTIAL | C6: Keep missing costs OPEN; never replace missing values with zero.
A7: Gross coverage | B7: =IF(AND(COUNT(Pricing!K2:K11)=10,COUNTIF(Pricing!D2:D11,Assumptions!B4)=10),"COMPLETE","PARTIAL") -> PARTIAL | C7: This model is a draft, not approval.
